hookmeup/__init__.py
hookmeup/__main__.py
hookmeup/hookmeup.py
hookmeup-1.0.5.dist-info/entry_points.txt
hookmeup-1.0.5.dist-info/LICENSE
hookmeup-1.0.5.dist-info/WHEEL
hookmeup-1.0.5.dist-info/METADATA
hookmeup-1.0.5.dist-info/RECORD
