Metadata-Version: 2.1
Name: hookmeup
Version: 1.0.5
Summary: A Git hook to automate your Pipenv and Django workflows
Home-page: https://git.danielmoch.com/hookmeup
License: UNKNOWN
Author: Daniel Moch
Author-email: daniel@danielmoch.com
Requires-Python: >=2.7
Classifier: License :: OSI Approved :: MIT License
Classifier: Development Status :: 5 - Production/Stable
Classifier: Environment :: Console
Classifier: Intended Audience :: Developers
Classifier: Operating System :: OS Independent
Classifier: Programming Language :: Python :: 2.7
Classifier: Programming Language :: Python :: 3
Classifier: Topic :: Software Development :: Version Control :: Git
Requires-Dist: pipenv; extra == "dev"
Provides-Extra: dev
